smartbar/__init__.py
smartbar/smartbar.py
smartbar/styles.py
smartbar-1.2.1.dist-info/LICENSE
smartbar-1.2.1.dist-info/METADATA
smartbar-1.2.1.dist-info/WHEEL
smartbar-1.2.1.dist-info/top_level.txt
smartbar-1.2.1.dist-info/RECORD
